README.md
autovega.py
setup.py
autovega.egg-info/PKG-INFO
autovega.egg-info/SOURCES.txt
autovega.egg-info/dependency_links.txt
autovega.egg-info/requires.txt
autovega.egg-info/top_level.txt