Metadata-Version: 1.1
Name: autovega
Version: 0.1.dev0
Summary: An IPython/Jupyter notebook widget for quick visualization of Pandas dataframes
Home-page: https://github.com/baldwint/autovega
Author: Tom Baldwin
Author-email: baldwint@baldwint.com
License: BSD 3-clause
Platform: UNKNOWN
Classifier: Development Status :: 3 - Alpha
Classifier: Framework :: Jupyter
Classifier: Framework :: IPython
Classifier: Intended Audience :: Science/Research
Classifier: Topic :: Scientific/Engineering :: Visualization
Classifier: License :: OSI Approved :: BSD License
Classifier: Programming Language :: Python
Classifier: Programming Language :: Python :: 3
Classifier: Programming Language :: Python :: 3.6
